odoo/addons/pos_stock_available_online/README.rst
odoo/addons/pos_stock_available_online/__init__.py
odoo/addons/pos_stock_available_online/__manifest__.py
odoo/addons/pos_stock_available_online/i18n/es.po
odoo/addons/pos_stock_available_online/i18n/it.po
odoo/addons/pos_stock_available_online/i18n/pos_stock_available_online.pot
odoo/addons/pos_stock_available_online/models/__init__.py
odoo/addons/pos_stock_available_online/models/pos_config.py
odoo/addons/pos_stock_available_online/models/pos_session.py
odoo/addons/pos_stock_available_online/models/res_config_settings.py
odoo/addons/pos_stock_available_online/models/stock_move.py
odoo/addons/pos_stock_available_online/models/stock_notifier_pos_mixin.py
odoo/addons/pos_stock_available_online/models/stock_quant.py
odoo/addons/pos_stock_available_online/models/stock_warehouse.py
odoo/addons/pos_stock_available_online/readme/CONFIGURE.rst
odoo/addons/pos_stock_available_online/readme/CONTRIBUTORS.rst
odoo/addons/pos_stock_available_online/readme/DESCRIPTION.rst
odoo/addons/pos_stock_available_online/readme/ROADMAP.rst
odoo/addons/pos_stock_available_online/static/description/banner.png
odoo/addons/pos_stock_available_online/static/description/icon.png
odoo/addons/pos_stock_available_online/static/description/index.html
odoo/addons/pos_stock_available_online/static/img/pos_config.png
odoo/addons/pos_stock_available_online/static/img/pos_quantity.png
odoo/addons/pos_stock_available_online/static/src/css/pos.css
odoo/addons/pos_stock_available_online/static/src/js/Screens/ProductScreen/ProductItem.esm.js
odoo/addons/pos_stock_available_online/static/src/js/Screens/ProductScreen/ProductsWidget.esm.js
odoo/addons/pos_stock_available_online/static/src/xml/Screens/ProductScreen/ProductItem.xml
odoo/addons/pos_stock_available_online/views/res_config_settings_view.xml
odoo_addon_pos_stock_available_online-16.0.2.0.3.1.dist-info/METADATA
odoo_addon_pos_stock_available_online-16.0.2.0.3.1.dist-info/WHEEL
odoo_addon_pos_stock_available_online-16.0.2.0.3.1.dist-info/top_level.txt
odoo_addon_pos_stock_available_online-16.0.2.0.3.1.dist-info/RECORD
