Metadata-Version: 2.1
Name: odoo-addon-pos_stock_available_online
Version: 16.0.2.0.3.1
Summary: Show the available quantity of products in the Point of Sale
Home-page: https://github.com/OCA/pos
Author: Cetmix, Odoo Community Association (OCA)
Author-email: support@odoo-community.org
License: AGPL-3
Classifier: Programming Language :: Python
Classifier: Framework :: Odoo
Classifier: Framework :: Odoo :: 16.0
Classifier: License :: OSI Approved :: GNU Affero General Public License v3
Requires-Python: >=3.10
Requires-Dist: odoo-addon-stock-available<16.1dev,>=16.0dev
Requires-Dist: odoo<16.1dev,>=16.0a
